itur/__init__.py
itur/__version__.py
itur/plotting.py
itur/utils.py
itur/data/1510/esatempr.npz
itur/data/1510/v0_lat.npz
itur/data/1510/v0_lon.npz
itur/data/1510/v0_temp.npz
itur/data/1510/v1_lat.npz
itur/data/1510/v1_lon.npz
itur/data/1510/v1_t_annual.npz
itur/data/1510/v1_t_month01.npz
itur/data/1510/v1_t_month02.npz
itur/data/1510/v1_t_month03.npz
itur/data/1510/v1_t_month04.npz
itur/data/1510/v1_t_month05.npz
itur/data/1510/v1_t_month06.npz
itur/data/1510/v1_t_month07.npz
itur/data/1510/v1_t_month08.npz
itur/data/1510/v1_t_month09.npz
itur/data/1510/v1_t_month10.npz
itur/data/1510/v1_t_month11.npz
itur/data/1510/v1_t_month12.npz
itur/data/1511/v1_lat.npz
itur/data/1511/v1_lon.npz
itur/data/1511/v1_topo_0dot5.npz
itur/data/1511/v2_egm2008.npz
itur/data/1511/v2_lat.npz
itur/data/1511/v2_lon.npz
itur/data/1511/v2_topo.npz
itur/data/453/v12_dn65m_00d10_v1.npz
itur/data/453/v12_dn65m_00d20_v1.npz
itur/data/453/v12_dn65m_00d50_v1.npz
itur/data/453/v12_dn65m_01d00_v1.npz
itur/data/453/v12_dn65m_02d00_v1.npz
itur/data/453/v12_dn65m_05d00_v1.npz
itur/data/453/v12_dn65m_10d00_v1.npz
itur/data/453/v12_dn65m_20d00_v1.npz
itur/data/453/v12_dn65m_30d00_v1.npz
itur/data/453/v12_dn65m_40d00_v1.npz
itur/data/453/v12_dn65m_50d00_v1.npz
itur/data/453/v12_dn65m_60d00_v1.npz
itur/data/453/v12_dn65m_70d00_v1.npz
itur/data/453/v12_dn65m_80d00_v1.npz
itur/data/453/v12_dn65m_90d00_v1.npz
itur/data/453/v12_dn65m_95d00_v1.npz
itur/data/453/v12_dn65m_98d00_v1.npz
itur/data/453/v12_dn65m_99d00_v1.npz
itur/data/453/v12_dn65m_99d50_v1.npz
itur/data/453/v12_dn65m_99d80_v1.npz
itur/data/453/v12_dn65m_99d90_v1.npz
itur/data/453/v12_dn_00d10_v1.npz
itur/data/453/v12_dn_00d20_v1.npz
itur/data/453/v12_dn_00d50_v1.npz
itur/data/453/v12_dn_01d00_v1.npz
itur/data/453/v12_dn_02d00_v1.npz
itur/data/453/v12_dn_05d00_v1.npz
itur/data/453/v12_dn_10d00_v1.npz
itur/data/453/v12_dn_20d00_v1.npz
itur/data/453/v12_dn_30d00_v1.npz
itur/data/453/v12_dn_40d00_v1.npz
itur/data/453/v12_dn_50d00_v1.npz
itur-0.4.0.dist-info/LICENSE.txt
itur-0.4.0.dist-info/METADATA
itur-0.4.0.dist-info/WHEEL
itur-0.4.0.dist-info/top_level.txt
itur-0.4.0.dist-info/RECORD
