Metadata-Version: 2.1
Name: itur
Version: 0.4.0
Summary: A python implementation of the ITU-R P. Recommendations
Home-page: https://github.com/inigodelportillo/ITU-Rpy
Author: Inigo del Portillo
Author-email: inigo.del.portillo@gmail.com
License: MIT
Project-URL: Bug Reports, https://github.com/inigodelportillo/ITU-Rpy/issues
Project-URL: Source, https://github.com/inigodelportillo/ITU-Rpy/
Keywords: atmopheric-propagation attenuation communications
Platform: UNKNOWN
Classifier: Development Status :: 3 - Alpha
Classifier: Intended Audience :: Telecommunications Industry
Classifier: Topic :: Scientific/Engineering :: Physics
Classifier: License :: OSI Approved :: MIT License
Classifier: Programming Language :: Python :: 3
Classifier: Programming Language :: Python :: 3.7
Classifier: Programming Language :: Python :: 3.8
Classifier: Programming Language :: Python :: 3.9
Classifier: Programming Language :: Python :: 3.10
Classifier: Programming Language :: Python :: 3.11
License-File: LICENSE.txt
